odoo/addons/l10n_pt_account_invoicexpress/README.rst
odoo/addons/l10n_pt_account_invoicexpress/__init__.py
odoo/addons/l10n_pt_account_invoicexpress/__manifest__.py
odoo/addons/l10n_pt_account_invoicexpress/data/country_mapping.txt
odoo/addons/l10n_pt_account_invoicexpress/data/mail_template.xml
odoo/addons/l10n_pt_account_invoicexpress/data/neutralize.sql
odoo/addons/l10n_pt_account_invoicexpress/data/res.country.csv
odoo/addons/l10n_pt_account_invoicexpress/i18n/l10n_pt_account_invoicexpress.pot
odoo/addons/l10n_pt_account_invoicexpress/i18n/pt.po
odoo/addons/l10n_pt_account_invoicexpress/models/__init__.py
odoo/addons/l10n_pt_account_invoicexpress/models/account_invoicexpress.py
odoo/addons/l10n_pt_account_invoicexpress/models/account_journal.py
odoo/addons/l10n_pt_account_invoicexpress/models/account_move.py
odoo/addons/l10n_pt_account_invoicexpress/models/account_tax.py
odoo/addons/l10n_pt_account_invoicexpress/models/res_company.py
odoo/addons/l10n_pt_account_invoicexpress/models/res_config_settings.py
odoo/addons/l10n_pt_account_invoicexpress/models/res_country.py
odoo/addons/l10n_pt_account_invoicexpress/models/res_partner.py
odoo/addons/l10n_pt_account_invoicexpress/readme/CONFIGURE.md
odoo/addons/l10n_pt_account_invoicexpress/readme/CONTRIBUTORS.md
odoo/addons/l10n_pt_account_invoicexpress/readme/DESCRIPTION.md
odoo/addons/l10n_pt_account_invoicexpress/readme/USAGE.md
odoo/addons/l10n_pt_account_invoicexpress/static/description/cover.png
odoo/addons/l10n_pt_account_invoicexpress/static/description/icon.png
odoo/addons/l10n_pt_account_invoicexpress/static/description/index.html
odoo/addons/l10n_pt_account_invoicexpress/tests/__init__.py
odoo/addons/l10n_pt_account_invoicexpress/tests/test_invoicexpress.py
odoo/addons/l10n_pt_account_invoicexpress/views/account_journal_view.xml
odoo/addons/l10n_pt_account_invoicexpress/views/account_move_view.xml
odoo/addons/l10n_pt_account_invoicexpress/views/account_tax_view.xml
odoo_addon_l10n_pt_account_invoicexpress-18.0.1.0.1.1.dist-info/METADATA
odoo_addon_l10n_pt_account_invoicexpress-18.0.1.0.1.1.dist-info/WHEEL
odoo_addon_l10n_pt_account_invoicexpress-18.0.1.0.1.1.dist-info/top_level.txt
odoo_addon_l10n_pt_account_invoicexpress-18.0.1.0.1.1.dist-info/RECORD
